README.md
setup.cfg
setup.py
facturacom/__init__.py
facturacom/api_wrapper.py
facturacom/catalogos.py
facturacom/cfdi.py
facturacom/clients.py
facturacom.egg-info/PKG-INFO
facturacom.egg-info/SOURCES.txt
facturacom.egg-info/dependency_links.txt
facturacom.egg-info/requires.txt
facturacom.egg-info/top_level.txt