Metadata-Version: 1.1
Name: facturacom
Version: 1.2.0
Summary: Integracion de factura.com
Home-page: https://github.com/richipargo/facturacom
Author: Ricardo Tapia
Author-email: rtapia92@gmail.com
License: UNKNOWN
Download-URL: https://github.com/richipargo/facturacom/archive/1.2.0.tar.gz
Keywords: testing,logging,example
Platform: UNKNOWN
